django_bbbc/__init__.py
django_bbbc/asgi.py
django_bbbc/celery.py
django_bbbc/settings.py
django_bbbc/urls.py
django_bbbc/wsgi.py
django_bbbc-0.1.0.dist-info/METADATA
django_bbbc-0.1.0.dist-info/WHEEL
django_bbbc-0.1.0.dist-info/RECORD
