Metadata-Version: 2.1
Name: django_bbbc
Version: 0.1.0
Summary: 
Author: niraj shrestha
Author-email: ns77851706@gmail.com
Requires-Python: >=3.10,<3.13
Classifier: Programming Language :: Python :: 3
Classifier: Programming Language :: Python :: 3.10
Classifier: Programming Language :: Python :: 3.11
Classifier: Programming Language :: Python :: 3.12
Requires-Dist: celery (>=5.3,<6.0)
Requires-Dist: django (>=5.0,<6.0)
Requires-Dist: django-celery-results (>=2.5.1,<3.0.0)
Requires-Dist: django-prometheus (>=2.3.1,<3.0.0)
Requires-Dist: django-statsd-mozilla (>=0.4.0,<0.5.0)
Requires-Dist: kombu (>=5.2.3,<6.0.0)
Requires-Dist: prometheus-client (>=0.20.0,<0.21.0)
Requires-Dist: psycopg2-binary (>=2.9.9,<3.0.0)
Requires-Dist: pydantic (>=1.10.5,<2.0.0)
Requires-Dist: pytest-watch (>=4.2.0,<5.0.0)
Requires-Dist: python-dotenv (>=1.0.1,<2.0.0)
Requires-Dist: python-json-logger (>=2.0.7,<3.0.0)
Requires-Dist: redis (>=5.0.6,<6.0.0)
